koshelevev1911/__init__.py
koshelevev1911/module.py
koshelevev1911-0.1.3.dist-info/licenses/LICENSE
koshelevev1911-0.1.3.dist-info/METADATA
koshelevev1911-0.1.3.dist-info/WHEEL
koshelevev1911-0.1.3.dist-info/top_level.txt
koshelevev1911-0.1.3.dist-info/RECORD
