Metadata-Version: 2.4
Name: koshelevev1911
Version: 0.1.3
Summary: Пакет с функцией hello world
Home-page: https://github.com/ваш-профиль/hello_world_package
Author: Кошелев Е. В.
Author-email: raygasada@gmail.com
Classifier: Programming Language :: Python :: 3
License-File: LICENSE
Dynamic: author
Dynamic: author-email
Dynamic: classifier
Dynamic: description
Dynamic: description-content-type
Dynamic: home-page
Dynamic: license-file
Dynamic: summary
